{
  "blocks": [
    {
      "block_no": 0,
      "line_number_start": 332,
      "line_number_end": 332,
      "code": "            lineRange: `Lines ${block.startLine + 1}-${block.endLine + 1} (${block.endLine - block.startLine + 1} lines)`, // Add line range and count",
      "timestamp": "2025-12-27T23:26:39.160Z",
      "file": "/Users/swarit-dev/voight/src/ui/segmentsWebviewProvider.ts"
    }
  ],
  "metadata": {
    "session": "2025-12-27T23-11-52-502Z",
    "totalBlocks": 1,
    "lastUpdated": "2025-12-27T23:26:39.162Z"
  }
}